README.md
setup.py
neptune/__init__.py
neptune/__main__.py
neptune/config.py
neptune/connector.py
neptune/engine.py
neptune/protocols/__init__.py
neptune/protocols/dispatcher.py
neptune/protocols/tcp/__init__.py
neptune/protocols/tcp/connect.py
neptune/protocols/tcp/protocol.py
neptune/protocols/udp/__init__.py
neptune/protocols/udp/connect.py
neptune/protocols/udp/protocol.py
neptune/resolver/__init__.py
neptune/resolver/dictionary/__init__.py
neptune/resolver/dictionary/connect.py
neptune/resolver/dictionary/resolver.py
neptune_dns_server.egg-info/PKG-INFO
neptune_dns_server.egg-info/SOURCES.txt
neptune_dns_server.egg-info/dependency_links.txt
neptune_dns_server.egg-info/requires.txt
neptune_dns_server.egg-info/top_level.txt